ryofaker/__init__.py
ryofaker/cli.py
ryofaker/config.py
ryofaker/exceptions.py
ryofaker/factory.py
ryofaker/generator.py
ryofaker/proxy.py
ryofaker/typing.py
ryofaker/schema/templates/ecommerce.json
ryofaker/schema/templates/finance.json
ryofaker/schema/templates/healthcare.json
ryofaker/schema/templates/telecom.json
ryofaker-1.0.0.dist-info/licenses/LICENSE
ryofaker-1.0.0.dist-info/METADATA
ryofaker-1.0.0.dist-info/WHEEL
ryofaker-1.0.0.dist-info/entry_points.txt
ryofaker-1.0.0.dist-info/top_level.txt
ryofaker-1.0.0.dist-info/zip-safe
ryofaker-1.0.0.dist-info/RECORD
