Metadata-Version: 2.4
Name: RyoFaker
Version: 1.0.0
Summary: Enterprise data generation library extending Faker
Home-page: https://github.com/ada/ryofaker
Author: ADA Data Science Team
Author-email: ADA Data Science Team <data-science@ada.com>
Maintainer-email: ADA Data Science Team <data-science@ada.com>
License: MIT
Project-URL: Homepage, https://github.com/ada/ryofaker
Project-URL: Documentation, https://ryofaker.readthedocs.io
Project-URL: Repository, https://github.com/ada/ryofaker
Project-URL: Issues, https://github.com/ada/ryofaker/issues
Project-URL: Changelog, https://github.com/ada/ryofaker/blob/main/CHANGELOG.md
Keywords: faker,fake,data,test,generator,fixtures,synthetic,schema,enterprise
Classifier: Development Status :: 4 - Beta
Classifier: Intended Audience :: Developers
Classifier: License :: OSI Approved :: MIT License
Classifier: Programming Language :: Python :: 3
Classifier: Programming Language :: Python :: 3.9
Classifier: Programming Language :: Python :: 3.10
Classifier: Programming Language :: Python :: 3.11
Classifier: Programming Language :: Python :: 3.12
Classifier: Topic :: Software Development :: Testing
Classifier: Typing :: Typed
Requires-Python: >=3.9
License-File: LICENSE
Requires-Dist: Faker>=20.0.0
Requires-Dist: pandas>=2.0.0
Requires-Dist: pyarrow>=10.0.0
Requires-Dist: pyyaml>=6.0
Requires-Dist: jsonschema>=4.0.0
Requires-Dist: networkx>=3.0
Requires-Dist: tqdm>=4.65.0
Provides-Extra: spark
Requires-Dist: pyspark>=3.4.0; extra == "spark"
Provides-Extra: cloud
Requires-Dist: oci>=2.100.0; extra == "cloud"
Requires-Dist: azure-storage-blob>=12.0.0; extra == "cloud"
Requires-Dist: boto3>=1.26.0; extra == "cloud"
Provides-Extra: dev
Requires-Dist: pytest>=7.4.0; extra == "dev"
Requires-Dist: pytest-cov>=4.1.0; extra == "dev"
Requires-Dist: black>=23.0.0; extra == "dev"
Requires-Dist: mypy>=1.5.0; extra == "dev"
Requires-Dist: sphinx>=7.0.0; extra == "dev"
Requires-Dist: sphinx-rtd-theme>=1.3.0; extra == "dev"
Requires-Dist: twine>=4.0.0; extra == "dev"
Requires-Dist: build>=0.10.0; extra == "dev"
Requires-Dist: ruff>=0.1.0; extra == "dev"
Provides-Extra: all
Requires-Dist: pyspark>=3.4.0; extra == "all"
Requires-Dist: oci>=2.100.0; extra == "all"
Requires-Dist: azure-storage-blob>=12.0.0; extra == "all"
Requires-Dist: boto3>=1.26.0; extra == "all"
Dynamic: author
Dynamic: home-page
Dynamic: license-file
Dynamic: requires-python
